aclt/__init__.py
aclt/main.py
aclt-1.0.0.dist-info/licenses/LICENSE
aclt-1.0.0.dist-info/METADATA
aclt-1.0.0.dist-info/WHEEL
aclt-1.0.0.dist-info/entry_points.txt
aclt-1.0.0.dist-info/top_level.txt
aclt-1.0.0.dist-info/RECORD
