Metadata-Version: 2.4
Name: aclt
Version: 1.0.0
Summary: Simple Windows AutoClicker with GUI
Author-email: TRC <trc@example.com>
License: Copyright (c) 2026 TRC-AI
Classifier: Programming Language :: Python :: 3
Classifier: Operating System :: Microsoft :: Windows
Classifier: License :: OSI Approved :: MIT License
Requires-Python: >=3.9
License-File: LICENSE
Requires-Dist: pyautogui
Requires-Dist: keyboard
Dynamic: license-file
